pycasreg/__init__.py
pycasreg/validation.py
pycasreg-0.1.0.dist-info/LICENSE
pycasreg-0.1.0.dist-info/METADATA
pycasreg-0.1.0.dist-info/WHEEL
pycasreg-0.1.0.dist-info/top_level.txt
pycasreg-0.1.0.dist-info/RECORD
