Metadata-Version: 2.1
Name: pycasreg
Version: 0.1.0
Summary: Chemical Abstracts Registry Service (CAS) helper Python package
Home-page: https://github.com/sami-m-g/pycasreg
Author: Mina Sami
Author-email: <sami.mg@outlook.com>
Maintainer: Mina Sami
Maintainer-email: <sami.mg@outlook.com>
License: BSD license
Project-URL: source, https://github.com/sami-m-g/pycasreg
Project-URL: homepage, https://github.com/sami-m-g/pycasreg
Project-URL: tracker, https://github.com/sami-m-g/pycasreg/issues
Keywords: "brightway","development"
Platform: any
Classifier: Development Status :: 4 - Beta
Classifier: Programming Language :: Python
Classifier: Programming Language :: Python :: 3
Classifier: Programming Language :: Python :: 3.8
Classifier: Programming Language :: Python :: 3.9
Classifier: Programming Language :: Python :: 3.10
Classifier: Programming Language :: Python :: 3.11
Requires-Python: >=3.8
Provides-Extra: testing
Provides-Extra: dev
License-File: LICENSE
